blepy/__init__.py
blepy/blepy.py
blepy-0.3.0.dist-info/LICENSE
blepy-0.3.0.dist-info/METADATA
blepy-0.3.0.dist-info/WHEEL
blepy-0.3.0.dist-info/top_level.txt
blepy-0.3.0.dist-info/RECORD
