Metadata-Version: 2.1
Name: blepy
Version: 0.3.0
Summary: A class-based wrapper for the peripheral functionalities provided by the library python-bluezero
Home-page: https://github.com/TrinaryLabs/blepy
Author: Trinary Labs
Author-email: f.v.carlsson@gmail.com
License: UNKNOWN
Project-URL: Bug Reports, https://github.com/TrinaryLabs/blepy/issues
Project-URL: Source, https://github.com/TrinaryLabs/blepy
Keywords: bluetooth,ble,bluez,linux
Platform: UNKNOWN
Classifier: Development Status :: 3 - Alpha
Classifier: Intended Audience :: Developers
Classifier: Intended Audience :: Education
Classifier: Topic :: System :: Hardware
Classifier: Topic :: Software Development :: Embedded Systems
Classifier: Topic :: Home Automation
Classifier: Topic :: Education
Classifier: License :: OSI Approved :: MIT License
Classifier: Programming Language :: Python :: 3 :: Only
Requires-Python: >=3.6, <4
Requires-Dist: bluezero
Provides-Extra: dev
Requires-Dist: check-manifest ; extra == 'dev'
Provides-Extra: test
Requires-Dist: coverage ; extra == 'test'
